{
  "schemaVersion": "1.3",
  "slug": "vaultfront",
  "name": "VaultFront",
  "status": "active",
  "health": "green",
  "currentFocus": "Session 63 audit+implement pass: launch-readiness endpoint, tournament bracket controls, test surface registration, revenue/free-tier posture.",
  "nextMilestone": "Run production build + E2E smoke, wire live revenue signal, and promote tournament playtest.",
  "blockers": [],
  "lastUpdated": "2026-06-03",
  "lifecycle": "alpha",
  "audience": "internal",
  "type": "game",
  "testingSurfaces": [
    {
      "type": "tests",
      "status": "green",
      "label": "Unit and server regression",
      "command": "npm test",
      "purpose": "Vitest core/client suite plus focused server tests."
    },
    {
      "type": "tests",
      "status": "green",
      "label": "Production build",
      "command": "npm run build-prod",
      "purpose": "TypeScript no-emit plus production Vite bundle."
    },
    {
      "type": "tests",
      "status": "green",
      "label": "E2E smoke",
      "command": "npm run e2e",
      "purpose": "Playwright homepage, settings, manifest, and solo-flow smoke."
    },
    {
      "type": "local",
      "status": "unknown",
      "label": "Local game server",
      "command": "npm run dev",
      "purpose": "Client and worker stack for manual match, tournament, and HUD checks."
    }
  ],
  "freeTierCostStatus": "exempt-internal",
  "revenueSignalStatus": "checkout-api-present-live-revenue-unverified",
  "readinessEndpoint": "/api/vaultfront/readiness",
  "truthAuditStatus": "green",
  "truthAuditLastRun": "2026-05-18",
  "silRubricVersion": "3.0",
  "silMax": 1000,
  "silScoreLegacy500": null,
  "silScore": 849,
  "silCategoriesV3": {
    "devHealth": 85,
    "creativeAlignment": 85,
    "momentum": 90,
    "engagement": 85,
    "processQuality": 80,
    "crossRepoCoherence": 93,
    "securityPosture": 90,
    "ecosystemIntegration": 65,
    "capitalEfficiency": 83,
    "automationCoverage": 93
  },
  "silScoreV3MigratedAt": "2026-04-21",
  "modelTier": "T1_sonnet",
  "modelTierDefault": "sonnet",
  "modelTierCtxLimit": 200000,
  "modelPlanMode": false,
  "modelPlanModeSlash": null,
  "ignisScore": 42978,
  "ignisGrade": "FORGE",
  "ignisLastComputed": "2026-06-03"
}
